Workbook

Sheet county_reeds_corrected0310
A1: NAME | B1: STATE_NAME | C1: STATE_FIPS | D1: CNTY_FIPS | E1: FIPS | F1: pFIPS | G1: DEMLAB | H1: PCA_REG
A2: Autauga | B2: Alabama | C2: 01 | D2: 001 | E2: 01001 | F2: p01001 | G2: 267 | H2: 90
A3: Baldwin | B3: Alabama | C3: 01 | D3: 003 | E3: 01003 | F3: p01003 | G3: 267 | H3: 90
A4: Barbour | B4: Alabama | C4: 01 | D4: 005 | E4: 01005 | F4: p01005 | G4: 267 | H4: 90
A5: Bibb | B5: Alabama | C5: 01 | D5: 007 | E5: 01007 | F5: p01007 | G5: 265 | H5: 89
A6: Blount | B6: Alabama | C6: 01 | D6: 009 | E6: 01009 | F6: p01009 | G6: 267 | H6: 90
A7: Bullock | B7: Alabama | C7: 01 | D7: 011 | E7: 01011 | F7: p01011 | G7: 267 | H7: 90
A8: Butler | B8: Alabama | C8: 01 | D8: 013 | E8: 01013 | F8: p01013 | G8: 267 | H8: 90
A9: Calhoun | B9: Alabama | C9: 01 | D9: 015 | E9: 01015 | F9: p01015 | G9: 267 | H9: 90
A10: Chambers | B10: Alabama | C10: 01 | D10: 017 | E10: 01017 | F10: p01017 | G10: 267 | H10: 90
A11: Cherokee | B11: Alabama | C11: 01 | D11: 019 | E11: 01019 | F11: p01019 | G11: 267 | H11: 90
A12: Chilton | B12: Alabama | C12: 01 | D12: 021 | E12: 01021 | F12: p01021 | G12: 267 | H12: 90
A13: Choctaw | B13: Alabama | C13: 01 | D13: 023 | E13: 01023 | F13: p01023 | G13: 265 | H13: 89
... A2385: Sanborn | B2385: South Dakota | C2385: 46 | D2385: 111 | E2385: 46111 | F2385: p46111 | G2385: 110 | H2385: 38
A2386: Oglala Lakota | B2386: South Dakota | C2386: 46 | D2386: 102 | E2386: 46102 | F2386: p46102 | G2386: 107 | H2386: 38
A2387: Spink | B2387: South Dakota | C2387: 46 | D2387: 115 | E2387: 46115 | F2387: p46115 | G2387: 109 | H2387: 38
A2388: Stanley | B2388: South Dakota | C2388: 46 | D2388: 117 | E2388: 46117 | F2388: p46117 | G2388: 106 | H2388: 38
A2389: Sully | B2389: South Dakota | C2389: 46 | D2389: 119 | E2389: 46119 | F2389: p46119 | G2389: 105 | H2389: 38
A2390: Todd | B2390: South Dakota | C2390: 46 | D2390: 121 | E2390: 46121 | F2390: p46121 | G2390: 108 | H2390: 38
A2391: Tripp | B2391: South Dakota | C2391: 46 | D2391: 123 | E2391: 46123 | F2391: p46123 | G2391: 108 | H2391: 38
A2392: Turner | B2392: South Dakota | C2392: 46 | D2392: 125 | E2392: 46125 | F2392: p46125 | G2392: 113 | H2392: 38
A2393: Union | B2393: South Dakota | C2393: 46 | D2393: 127 | E2393: 46127 | F2393: p46127 | G2393: 113 | H2393: 38
A2394: Walworth | B2394: South Dakota | C2394: 46 | D2394: 129 | E2394: 46129 | F2394: p46129 | G2394: 105 | H2394: 38
A2395: Yankton | B2395: South Dakota | C2395: 46 | D2395: 135 | E2395: 46135 | F2395: p46135 | G2395: 111 | H2395: 38
A2396: Ziebach | B2396: South Dakota | C2396: 46 | D2396: 137 | E2396: 46137 | F2396: p46137 | G2396: 105 | H2396: 38
A2397: Anderson | B2397: Tennessee | C2397: 47 | D2397: 001 | E2397: 47001 | F2397: p47001 | G2397: 281 | H2397: 92
A2398: Bedford | B2398: Tennessee | C2398: 47 | D2398: 003 | E2398: 47003 | F2398: p47003 | G2398: 279 | H2398: 92
... A3110: Weston | B3110: Wyoming | C3110: 56 | D3110: 045 | E3110: 56045 | F3110: p56045 | G3110: 73 | H3110: 23

Sheet fromanthony01062012
A1: county | B1: state | C1: stateAbb | D1: id | E1: alternative_id | F1: cnty_fips | G1: reeds_reg | H1: PCA | I1: from anthony 01-06-2012
A2: Autauga | B2: Alabama | C2: =VLOOKUP(B2,StateAbb!$A$3:$C$62,3,FALSE()) -> AL | D2: Autauga-Alabama | E2: =CONCATENATE(C2,A2) -> ALAutauga | F2: 1 | G2: 267 | H2: =IFERROR(VLOOKUP(G2,county_reeds_corrected0310!$G$1:$H$3110,2,FALSE()),0) -> 90
A3: Baldwin | B3: Alabama | C3: =VLOOKUP(B3,StateAbb!$A$3:$C$62,3,FALSE()) -> AL | D3: Baldwin-Alabama | E3: =CONCATENATE(C3,A3) -> ALBaldwin | F3: 3 | G3: 267 | H3: =IFERROR(VLOOKUP(G3,county_reeds_corrected0310!$G$1:$H$3110,2,FALSE()),0) -> 90
A4: Barbour | B4: Alabama | C4: =VLOOKUP(B4,StateAbb!$A$3:$C$62,3,FALSE()) -> AL | D4: Barbour-Alabama | E4: =CONCATENATE(C4,A4) -> ALBarbour | F4: 5 | G4: 267 | H4: =IFERROR(VLOOKUP(G4,county_reeds_corrected0310!$G$1:$H$3110,2,FALSE()),0) -> 90
A5: Bibb | B5: Alabama | C5: =VLOOKUP(B5,StateAbb!$A$3:$C$62,3,FALSE()) -> AL | D5: Bibb-Alabama | E5: =CONCATENATE(C5,A5) -> ALBibb | F5: 7 | G5: 265 | H5: =IFERROR(VLOOKUP(G5,county_reeds_corrected0310!$G$1:$H$3110,2,FALSE()),0) -> 89
A6: Blount | B6: Alabama | C6: =VLOOKUP(B6,StateAbb!$A$3:$C$62,3,FALSE()) -> AL | D6: Blount-Alabama | E6: =CONCATENATE(C6,A6) -> ALBlount | F6: 9 | G6: 267 | H6: =IFERROR(VLOOKUP(G6,county_reeds_corrected0310!$G$1:$H$3110,2,FALSE()),0) -> 90
A7: Bullock | B7: Alabama | C7: =VLOOKUP(B7,StateAbb!$A$3:$C$62,3,FALSE()) -> AL | D7: Bullock-Alabama | E7: =CONCATENATE(C7,A7) -> ALBullock | F7: 11 | G7: 267 | H7: =IFERROR(VLOOKUP(G7,county_reeds_corrected0310!$G$1:$H$3110,2,FALSE()),0) -> 90
A8: Butler | B8: Alabama | C8: =VLOOKUP(B8,StateAbb!$A$3:$C$62,3,FALSE()) -> AL | D8: Butler-Alabama | E8: =CONCATENATE(C8,A8) -> ALButler | F8: 13 | G8: 267 | H8: =IFERROR(VLOOKUP(G8,county_reeds_corrected0310!$G$1:$H$3110,2,FALSE()),0) -> 90
A9: Calhoun | B9: Alabama | C9: =VLOOKUP(B9,StateAbb!$A$3:$C$62,3,FALSE()) -> AL | D9: Calhoun-Alabama | E9: =CONCATENATE(C9,A9) -> ALCalhoun | F9: 15 | G9: 267 | H9: =IFERROR(VLOOKUP(G9,county_reeds_corrected0310!$G$1:$H$3110,2,FALSE()),0) -> 90
A10: Chambers | B10: Alabama | C10: =VLOOKUP(B10,StateAbb!$A$3:$C$62,3,FALSE()) -> AL | D10: Chambers-Alabama | E10: =CONCATENATE(C10,A10) -> ALChambers | F10: 17 | G10: 267 | H10: =IFERROR(VLOOKUP(G10,county_reeds_corrected0310!$G$1:$H$3110,2,FALSE()),0) -> 90
A11: Cherokee | B11: Alabama | C11: =VLOOKUP(B11,StateAbb!$A$3:$C$62,3,FALSE()) -> AL | D11: Cherokee-Alabama | E11: =CONCATENATE(C11,A11) -> ALCherokee | F11: 19 | G11: 267 | H11: =IFERROR(VLOOKUP(G11,county_reeds_corrected0310!$G$1:$H$3110,2,FALSE()),0) -> 90
A12: Chilton | B12: Alabama | C12: =VLOOKUP(B12,StateAbb!$A$3:$C$62,3,FALSE()) -> AL | D12: Chilton-Alabama | E12: =CONCATENATE(C12,A12) -> ALChilton | F12: 21 | G12: 267 | H12: =IFERROR(VLOOKUP(G12,county_reeds_corrected0310!$G$1:$H$3110,2,FALSE()),0) -> 90
A13: Choctaw | B13: Alabama | C13: =VLOOKUP(B13,StateAbb!$A$3:$C$62,3,FALSE()) -> AL | D13: Choctaw-Alabama | E13: =CONCATENATE(C13,A13) -> ALChoctaw | F13: 23 | G13: 265 | H13: =IFERROR(VLOOKUP(G13,county_reeds_corrected0310!$G$1:$H$3110,2,FALSE()),0) -> 89
... A68: Winston | B68: Alabama | C68: =VLOOKUP(B68,StateAbb!$A$3:$C$62,3,FALSE()) -> AL | D68: Winston-Alabama | E68: =CONCATENATE(C68,A68) -> ALWinston | F68: 133 | G68: 265 | H68: =IFERROR(VLOOKUP(G68,county_reeds_corrected0310!$G$1:$H$3110,2,FALSE()),0) -> 89
A69: Aleutians East | B69: Alaska | C69: =VLOOKUP(B69,StateAbb!$A$3:$C$62,3,FALSE()) -> AK | D69: Aleutians East-Alaska | E69: =CONCATENATE(C69,A69) -> AKAleutians East | F69: 13 | H69: =IFERROR(VLOOKUP(G69,county_reeds_corrected0310!$G$1:$H$3110,2,FALSE()),0) -> 0
A70: Aleutians West | B70: Alaska | C70: =VLOOKUP(B70,StateAbb!$A$3:$C$62,3,FALSE()) -> AK | D70: Aleutians West-Alaska | E70: =CONCATENATE(C70,A70) -> AKAleutians West | F70: 16 | H70: =IFERROR(VLOOKUP(G70,county_reeds_corrected0310!$G$1:$H$3110,2,FALSE()),0) -> 0
A71: Anchorage | B71: Alaska | C71: =VLOOKUP(B71,StateAbb!$A$3:$C$62,3,FALSE()) -> AK | D71: Anchorage-Alaska | E71: =CONCATENATE(C71,A71) -> AKAnchorage | F71: 20 | H71: =IFERROR(VLOOKUP(G71,county_reeds_corrected0310!$G$1:$H$3110,2,FALSE()),0) -> 0
A72: Bethel | B72: Alaska | C72: =VLOOKUP(B72,StateAbb!$A$3:$C$62,3,FALSE()) -> AK | D72: Bethel-Alaska | E72: =CONCATENATE(C72,A72) -> AKBethel | F72: 50 | H72: =IFERROR(VLOOKUP(G72,county_reeds_corrected0310!$G$1:$H$3110,2,FALSE()),0) -> 0
A73: Bristol Bay | B73: Alaska | C73: =VLOOKUP(B73,StateAbb!$A$3:$C$62,3,FALSE()) -> AK | D73: Bristol Bay-Alaska | E73: =CONCATENATE(C73,A73) -> AKBristol Bay | F73: 60 | H73: =IFERROR(VLOOKUP(G73,county_reeds_corrected0310!$G$1:$H$3110,2,FALSE()),0) -> 0
A74: Denali | B74: Alaska | C74: =VLOOKUP(B74,StateAbb!$A$3:$C$62,3,FALSE()) -> AK | D74: Denali-Alaska | E74: =CONCATENATE(C74,A74) -> AKDenali | F74: 68 | H74: =IFERROR(VLOOKUP(G74,county_reeds_corrected0310!$G$1:$H$3110,2,FALSE()),0) -> 0
A75: Dillingham | B75: Alaska | C75: =VLOOKUP(B75,StateAbb!$A$3:$C$62,3,FALSE()) -> AK | D75: Dillingham-Alaska | E75: =CONCATENATE(C75,A75) -> AKDillingham | F75: 70 | H75: =IFERROR(VLOOKUP(G75,county_reeds_corrected0310!$G$1:$H$3110,2,FALSE()),0) -> 0
A76: Fairbanks North Star | B76: Alaska | C76: =VLOOKUP(B76,StateAbb!$A$3:$C$62,3,FALSE()) -> AK | D76: Fairbanks North Star-Alaska | E76: =CONCATENATE(C76,A76) -> AKFairbanks North Star | F76: 90 | H76: =IFERROR(VLOOKUP(G76,county_reeds_corrected0310!$G$1:$H$3110,2,FALSE()),0) -> 0
A77: Haines | B77: Alaska | C77: =VLOOKUP(B77,StateAbb!$A$3:$C$62,3,FALSE()) -> AK | D77: Haines-Alaska | E77: =CONCATENATE(C77,A77) -> AKHaines | F77: 100 | H77: =IFERROR(VLOOKUP(G77,county_reeds_corrected0310!$G$1:$H$3110,2,FALSE()),0) -> 0
A78: Juneau | B78: Alaska | C78: =VLOOKUP(B78,StateAbb!$A$3:$C$62,3,FALSE()) -> AK | D78: Juneau-Alaska | E78: =CONCATENATE(C78,A78) -> AKJuneau | F78: 110 | H78: =IFERROR(VLOOKUP(G78,county_reeds_corrected0310!$G$1:$H$3110,2,FALSE()),0) -> 0
A79: Kenai Peninsula | B79: Alaska | C79: =VLOOKUP(B79,StateAbb!$A$3:$C$62,3,FALSE()) -> AK | D79: Kenai Peninsula-Alaska | E79: =CONCATENATE(C79,A79) -> AKKenai Peninsula | F79: 122 | H79: =IFERROR(VLOOKUP(G79,county_reeds_corrected0310!$G$1:$H$3110,2,FALSE()),0) -> 0
A80: Ketchikan Gateway | B80: Alaska | C80: =VLOOKUP(B80,StateAbb!$A$3:$C$62,3,FALSE()) -> AK | D80: Ketchikan Gateway-Alaska | E80: =CONCATENATE(C80,A80) -> AKKetchikan Gateway | F80: 130 | H80: =IFERROR(VLOOKUP(G80,county_reeds_corrected0310!$G$1:$H$3110,2,FALSE()),0) -> 0
... A95: Yukon-Koyukuk | B95: Alaska | C95: =VLOOKUP(B95,StateAbb!$A$3:$C$62,3,FALSE()) -> AK | D95: Yukon-Koyukuk-Alaska | E95: =CONCATENATE(C95,A95) -> AKYukon-Koyukuk | F95: 290 | H95: =IFERROR(VLOOKUP(G95,county_reeds_corrected0310!$G$1:$H$3110,2,FALSE()),0) -> 0
A96: Apache | B96: Arizona | C96: =VLOOKUP(B96,StateAbb!$A$3:$C$62,3,FALSE()) -> AZ | D96: Apache-Arizona | E96: =CONCATENATE(C96,A96) -> AZApache | F96: 1 | G96: 55 | H96: =IFERROR(VLOOKUP(G96,county_reeds_corrected0310!$G$1:$H$3110,2,FALSE()),0) -> 29
A97: Cochise | B97: Arizona | C97: =VLOOKUP(B97,StateAbb!$A$3:$C$62,3,FALSE()) -> AZ | D97: Cochise-Arizona | E97: =CONCATENATE(C97,A97) -> AZCochise | F97: 3 | G97: 59 | H97: =IFERROR(VLOOKUP(G97,county_reeds_corrected0310!$G$1:$H$3110,2,FALSE()),0) -> 28
A98: Coconino | B98: Arizona | C98: =VLOOKUP(B98,StateAbb!$A$3:$C$62,3,FALSE()) -> AZ | D98: Coconino-Arizona | E98: =CONCATENATE(C98,A98) -> AZCoconino | F98: 5 | G98: 54 | H98: =IFERROR(VLOOKUP(G98,county_reeds_corrected0310!$G$1:$H$3110,2,FALSE()),0) -> 28
A99: Gila | B99: Arizona | C99: =VLOOKUP(B99,StateAbb!$A$3:$C$62,3,FALSE()) -> AZ | D99: Gila-Arizona | E99: =CONCATENATE(C99,A99) -> AZGila | F99: 7 | G99: 59 | H99: =IFERROR(VLOOKUP(G99,county_reeds_corrected0310!$G$1:$H$3110,2,FALSE()),0) -> 28
A100: Graham | B100: Arizona | C100: =VLOOKUP(B100,StateAbb!$A$3:$C$62,3,FALSE()) -> AZ | D100: Graham-Arizona | E100: =CONCATENATE(C100,A100) -> AZGraham | F100: 9 | G100: 59 | H100: =IFERROR(VLOOKUP(G100,county_reeds_corrected0310!$G$1:$H$3110,2,FALSE()),0) -> 28
A101: Greenlee | B101: Arizona | C101: =VLOOKUP(B101,StateAbb!$A$3:$C$62,3,FALSE()) -> AZ | D101: Greenlee-Arizona | E101: =CONCATENATE(C101,A101) -> AZGreenlee | F101: 11 | G101: 59 | H101: =IFERROR(VLOOKUP(G101,county_reeds_corrected0310!$G$1:$H$3110,2,FALSE()),0) -> 28
A102: La Paz | B102: Arizona | C102: =VLOOKUP(B102,StateAbb!$A$3:$C$62,3,FALSE()) -> AZ | D102: La Paz-Arizona | E102: =CONCATENATE(C102,A102) -> AZLa Paz | F102: 12 | G102: 56 | H102: =IFERROR(VLOOKUP(G102,county_reeds_corrected0310!$G$1:$H$3110,2,FALSE()),0) -> 28
A103: Maricopa | B103: Arizona | C103: =VLOOKUP(B103,StateAbb!$A$3:$C$62,3,FALSE()) -> AZ | D103: Maricopa-Arizona | E103: =CONCATENATE(C103,A103) -> AZMaricopa | F103: 13 | G103: 57 | H103: =IFERROR(VLOOKUP(G103,county_reeds_corrected0310!$G$1:$H$3110,2,FALSE()),0) -> 28
A104: Mohave | B104: Arizona | C104: =VLOOKUP(B104,StateAbb!$A$3:$C$62,3,FALSE()) -> AZ | D104: Mohave-Arizona | E104: =CONCATENATE(C104,A104) -> AZMohave | F104: 15 | G104: 53 | H104: =IFERROR(VLOOKUP(G104,county_reeds_corrected0310!$G$1:$H$3110,2,FALSE()),0) -> 27
A105: Navajo | B105: Arizona | C105: =VLOOKUP(B105,StateAbb!$A$3:$C$62,3,FALSE()) -> AZ | D105: Navajo-Arizona | E105: =CONCATENATE(C105,A105) -> AZNavajo | F105: 17 | G105: 54 | H105: =IFERROR(VLOOKUP(G105,county_reeds_corrected0310!$G$1:$H$3110,2,FALSE()),0) -> 28
A106: Pima | B106: Arizona | C106: =VLOOKUP(B106,StateAbb!$A$3:$C$62,3,FALSE()) -> AZ | D106: Pima-Arizona | E106: =CONCATENATE(C106,A106) -> AZPima | F106: 19 | G106: 58 | H106: =IFERROR(VLOOKUP(G106,county_reeds_corrected0310!$G$1:$H$3110,2,FALSE()),0) -> 30
A107: Pinal | B107: Arizona | C107: =VLOOKUP(B107,StateAbb!$A$3:$C$62,3,FALSE()) -> AZ | D107: Pinal-Arizona | E107: =CONCATENATE(C107,A107) -> AZPinal | F107: 21 | G107: 57 | H107: =IFERROR(VLOOKUP(G107,county_reeds_corrected0310!$G$1:$H$3110,2,FALSE()),0) -> 28
... A545: Worth | B545: Georgia | C545: =VLOOKUP(B545,StateAbb!$A$3:$C$62,3,FALSE()) -> GA | D545: Worth-Georgia | E545: =CONCATENATE(C545,A545) -> GAWorth | F545: 321 | G545: 275 | H545: =IFERROR(VLOOKUP(G545,county_reeds_corrected0310!$G$1:$H$3110,2,FALSE()),0) -> 94
A546: Hawaii | B546: Hawaii | C546: =VLOOKUP(B546,StateAbb!$A$3:$C$62,3,FALSE()) -> HI | D546: Hawaii-Hawaii | E546: =CONCATENATE(C546,A546) -> HIHawaii | F546: 1 | H546: =IFERROR(VLOOKUP(G546,county_reeds_corrected0310!$G$1:$H$3110,2,FALSE()),0) -> 0
A547: Honolulu | B547: Hawaii | C547: =VLOOKUP(B547,StateAbb!$A$3:$C$62,3,FALSE()) -> HI | D547: Honolulu-Hawaii | E547: =CONCATENATE(C547,A547) -> HIHonolulu | F547: 3 | H547: =IFERROR(VLOOKUP(G547,county_reeds_corrected0310!$G$1:$H$3110,2,FALSE()),0) -> 0
A548: Kalawao | B548: Hawaii | C548: =VLOOKUP(B548,StateAbb!$A$3:$C$62,3,FALSE()) -> HI | D548: Kalawao-Hawaii | E548: =CONCATENATE(C548,A548) -> HIKalawao | F548: 5 | H548: =IFERROR(VLOOKUP(G548,county_reeds_corrected0310!$G$1:$H$3110,2,FALSE()),0) -> 0
A549: Kauai | B549: Hawaii | C549: =VLOOKUP(B549,StateAbb!$A$3:$C$62,3,FALSE()) -> HI | D549: Kauai-Hawaii | E549: =CONCATENATE(C549,A549) -> HIKauai | F549: 7 | H549: =IFERROR(VLOOKUP(G549,county_reeds_corrected0310!$G$1:$H$3110,2,FALSE()),0) -> 0
A550: Maui | B550: Hawaii | C550: =VLOOKUP(B550,StateAbb!$A$3:$C$62,3,FALSE()) -> HI | D550: Maui-Hawaii | E550: =CONCATENATE(C550,A550) -> HIMaui | F550: 9 | H550: =IFERROR(VLOOKUP(G550,county_reeds_corrected0310!$G$1:$H$3110,2,FALSE()),0) -> 0
A551: Ada | B551: Idaho | C551: =VLOOKUP(B551,StateAbb!$A$3:$C$62,3,FALSE()) -> ID | D551: Ada-Idaho | E551: =CONCATENATE(C551,A551) -> IDAda | F551: 1 | G551: 44 | H551: =IFERROR(VLOOKUP(G551,county_reeds_corrected0310!$G$1:$H$3110,2,FALSE()),0) -> 15
A552: Adams | B552: Idaho | C552: =VLOOKUP(B552,StateAbb!$A$3:$C$62,3,FALSE()) -> ID | D552: Adams-Idaho | E552: =CONCATENATE(C552,A552) -> IDAdams | F552: 3 | G552: 42 | H552: =IFERROR(VLOOKUP(G552,county_reeds_corrected0310!$G$1:$H$3110,2,FALSE()),0) -> 15
A553: Bannock | B553: Idaho | C553: =VLOOKUP(B553,StateAbb!$A$3:$C$62,3,FALSE()) -> ID | D553: Bannock-Idaho | E553: =CONCATENATE(C553,A553) -> IDBannock | F553: 5 | G553: 46 | H553: =IFERROR(VLOOKUP(G553,county_reeds_corrected0310!$G$1:$H$3110,2,FALSE()),0) -> 16
A554: Bear Lake | B554: Idaho | C554: =VLOOKUP(B554,StateAbb!$A$3:$C$62,3,FALSE()) -> ID | D554: Bear Lake-Idaho | E554: =CONCATENATE(C554,A554) -> IDBear Lake | F554: 7 | G554: 47 | H554: =IFERROR(VLOOKUP(G554,county_reeds_corrected0310!$G$1:$H$3110,2,FALSE()),0) -> 16
A555: Benewah | B555: Idaho | C555: =VLOOKUP(B555,StateAbb!$A$3:$C$62,3,FALSE()) -> ID | D555: Benewah-Idaho | E555: =CONCATENATE(C555,A555) -> IDBenewah | F555: 9 | G555: 41 | H555: =IFERROR(VLOOKUP(G555,county_reeds_corrected0310!$G$1:$H$3110,2,FALSE()),0) -> 14
A556: Bingham | B556: Idaho | C556: =VLOOKUP(B556,StateAbb!$A$3:$C$62,3,FALSE()) -> ID | D556: Bingham-Idaho | E556: =CONCATENATE(C556,A556) -> IDBingham | F556: 11 | G556: 47 | H556: =IFERROR(VLOOKUP(G556,county_reeds_corrected0310!$G$1:$H$3110,2,FALSE()),0) -> 16
A557: Blaine | B557: Idaho | C557: =VLOOKUP(B557,StateAbb!$A$3:$C$62,3,FALSE()) -> ID | D557: Blaine-Idaho | E557: =CONCATENATE(C557,A557) -> IDBlaine | F557: 13 | G557: 45 | H557: =IFERROR(VLOOKUP(G557,county_reeds_corrected0310!$G$1:$H$3110,2,FALSE()),0) -> 15
A558: Boise | B558: Idaho | C558: =VLOOKUP(B558,StateAbb!$A$3:$C$62,3,FALSE()) -> ID | D558: Boise-Idaho | E558: =CONCATENATE(C558,A558) -> IDBoise | F558: 15 | G558: 42 | H558: =IFERROR(VLOOKUP(G558,county_reeds_corrected0310!$G$1:$H$3110,2,FALSE()),0) -> 15
A559: Bonner | B559: Idaho | C559: =VLOOKUP(B559,StateAbb!$A$3:$C$62,3,FALSE()) -> ID | D559: Bonner-Idaho | E559: =CONCATENATE(C559,A559) -> IDBonner | F559: 17 | G559: 41 | H559: =IFERROR(VLOOKUP(G559,county_reeds_corrected0310!$G$1:$H$3110,2,FALSE()),0) -> 14
A560: Bonneville | B560: Idaho | C560: =VLOOKUP(B560,StateAbb!$A$3:$C$62,3,FALSE()) -> ID | D560: Bonneville-Idaho | E560: =CONCATENATE(C560,A560) -> IDBonneville | F560: 19 | G560: 47 | H560: =IFERROR(VLOOKUP(G560,county_reeds_corrected0310!$G$1:$H$3110,2,FALSE()),0) -> 16
A561: Boundary | B561: Idaho | C561: =VLOOKUP(B561,StateAbb!$A$3:$C$62,3,FALSE()) -> ID | D561: Boundary-Idaho | E561: =CONCATENATE(C561,A561) -> IDBoundary | F561: 21 | G561: 41 | H561: =IFERROR(VLOOKUP(G561,county_reeds_corrected0310!$G$1:$H$3110,2,FALSE()),0) -> 14
A562: Butte | B562: Idaho | C562: =VLOOKUP(B562,StateAbb!$A$3:$C$62,3,FALSE()) -> ID | D562: Butte-Idaho | E562: =CONCATENATE(C562,A562) -> IDButte | F562: 23 | G562: 43 | H562: =IFERROR(VLOOKUP(G562,county_reeds_corrected0310!$G$1:$H$3110,2,FALSE()),0) -> 15
... A1955: Northampton | B1955: North Carolina | C1955: =VLOOKUP(B1955,StateAbb!$A$3:$C$62,3,FALSE()) -> NC | D1955: Northampton-North Carolina | E1955: =CONCATENATE(C1955,A1955) -> NCNorthampton | F1955: 131 | G1955: 293 | H1955: =IFERROR(VLOOKUP(G1955,county_reeds_corrected0310!$G$1:$H$3110,2,FALSE()),0) -> 98
A1956: Onslow | B1956: North Carolina | C1956: =VLOOKUP(B1956,StateAbb!$A$3:$C$62,3,FALSE()) -> NC | D1956: Onslow-North Carolina | E1956: =CONCATENATE(C1956,A1956) -> NCOnslow | F1956: 133 | H1956: =IFERROR(VLOOKUP(G1956,county_reeds_corrected0310!$G$1:$H$3110,2,FALSE()),0) -> 0
A1957: Orange | B1957: North Carolina | C1957: =VLOOKUP(B1957,StateAbb!$A$3:$C$62,3,FALSE()) -> NC | D1957: Orange-North Carolina | E1957: =CONCATENATE(C1957,A1957) -> NCOrange | F1957: 135 | G1957: 291 | H1957: =IFERROR(VLOOKUP(G1957,county_reeds_corrected0310!$G$1:$H$3110,2,FALSE()),0) -> 98
A1958: Pamlico | B1958: North Carolina | C1958: =VLOOKUP(B1958,StateAbb!$A$3:$C$62,3,FALSE()) -> NC | D1958: Pamlico-North Carolina | E1958: =CONCATENATE(C1958,A1958) -> NCPamlico | F1958: 137 | G1958: 294 | H1958: =IFERROR(VLOOKUP(G1958,county_reeds_corrected0310!$G$1:$H$3110,2,FALSE()),0) -> 98
A1959: Pasquotank | B1959: North Carolina | C1959: =VLOOKUP(B1959,StateAbb!$A$3:$C$62,3,FALSE()) -> NC | D1959: Pasquotank-North Carolina | E1959: =CONCATENATE(C1959,A1959) -> NCPasquotank | F1959: 139 | G1959: 294 | H1959: =IFERROR(VLOOKUP(G1959,county_reeds_corrected0310!$G$1:$H$3110,2,FALSE()),0) -> 98
A1960: Pender | B1960: North Carolina | C1960: =VLOOKUP(B1960,StateAbb!$A$3:$C$62,3,FALSE()) -> NC | D1960: Pender-North Carolina | E1960: =CONCATENATE(C1960,A1960) -> NCPender | F1960: 141 | G1960: 293 | H1960: =IFERROR(VLOOKUP(G1960,county_reeds_corrected0310!$G$1:$H$3110,2,FALSE()),0) -> 98
A1961: Perquimans | B1961: North Carolina | C1961: =VLOOKUP(B1961,StateAbb!$A$3:$C$62,3,FALSE()) -> NC | D1961: Perquimans-North Carolina | E1961: =CONCATENATE(C1961,A1961) -> NCPerquimans | F1961: 143 | G1961: 294 | H1961: =IFERROR(VLOOKUP(G1961,county_reeds_corrected0310!$G$1:$H$3110,2,FALSE()),0) -> 98
A1962: Person | B1962: North Carolina | C1962: =VLOOKUP(B1962,StateAbb!$A$3:$C$62,3,FALSE()) -> NC | D1962: Person-North Carolina | E1962: =CONCATENATE(C1962,A1962) -> NCPerson | F1962: 145 | G1962: 291 | H1962: =IFERROR(VLOOKUP(G1962,county_reeds_corrected0310!$G$1:$H$3110,2,FALSE()),0) -> 98
A1963: Pitt | B1963: North Carolina | C1963: =VLOOKUP(B1963,StateAbb!$A$3:$C$62,3,FALSE()) -> NC | D1963: Pitt-North Carolina | E1963: =CONCATENATE(C1963,A1963) -> NCPitt | F1963: 147 | G1963: 293 | H1963: =IFERROR(VLOOKUP(G1963,county_reeds_corrected0310!$G$1:$H$3110,2,FALSE()),0) -> 98
A1964: Polk | B1964: North Carolina | C1964: =VLOOKUP(B1964,StateAbb!$A$3:$C$62,3,FALSE()) -> NC | D1964: Polk-North Carolina | E1964: =CONCATENATE(C1964,A1964) -> NCPolk | F1964: 149 | G1964: 288 | H1964: =IFERROR(VLOOKUP(G1964,county_reeds_corrected0310!$G$1:$H$3110,2,FALSE()),0) -> 97
A1965: Randolph | B1965: North Carolina | C1965: =VLOOKUP(B1965,StateAbb!$A$3:$C$62,3,FALSE()) -> NC | D1965: Randolph-North Carolina | E1965: =CONCATENATE(C1965,A1965) -> NCRandolph | F1965: 151 | G1965: 289 | H1965: =IFERROR(VLOOKUP(G1965,county_reeds_corrected0310!$G$1:$H$3110,2,FALSE()),0) -> 97
A1966: Richmond | B1966: North Carolina | C1966: =VLOOKUP(B1966,StateAbb!$A$3:$C$62,3,FALSE()) -> NC | D1966: Richmond-North Carolina | E1966: =CONCATENATE(C1966,A1966) -> NCRichmond | F1966: 153 | G1966: 292 | H1966: =IFERROR(VLOOKUP(G1966,county_reeds_corrected0310!$G$1:$H$3110,2,FALSE()),0) -> 98
A1967: Robeson | B1967: North Carolina | C1967: =VLOOKUP(B1967,StateAbb!$A$3:$C$62,3,FALSE()) -> NC | D1967: Robeson-North Carolina | E1967: =CONCATENATE(C1967,A1967) -> NCRobeson | F1967: 155 | G1967: 292 | H1967: =IFERROR(VLOOKUP(G1967,county_reeds_corrected0310!$G$1:$H$3110,2,FALSE()),0) -> 98
A1968: Rockingham | B1968: North Carolina | C1968: =VLOOKUP(B1968,StateAbb!$A$3:$C$62,3,FALSE()) -> NC | D1968: Rockingham-North Carolina | E1968: =CONCATENATE(C1968,A1968) -> NCRockingham | F1968: 157 | G1968: 289 | H1968: =IFERROR(VLOOKUP(G1968,county_reeds_corrected0310!$G$1:$H$3110,2,FALSE()),0) -> 97
... A2967: Grays Harbor | B2967: Washington | C2967: =VLOOKUP(B2967,StateAbb!$A$3:$C$62,3,FALSE()) -> WA | D2967: Grays Harbor-Washington | E2967: =CONCATENATE(C2967,A2967) -> WAGrays Harbor | F2967: 27 | G2967: 1 | H2967: =IFERROR(VLOOKUP(G2967,county_reeds_corrected0310!$G$1:$H$3110,2,FALSE()),0) -> 2
A2968: Island | B2968: Washington | C2968: =VLOOKUP(B2968,StateAbb!$A$3:$C$62,3,FALSE()) -> WA | D2968: Island-Washington | E2968: =CONCATENATE(C2968,A2968) -> WAIsland | F2968: 29 | H2968: =IFERROR(VLOOKUP(G2968,county_reeds_corrected0310!$G$1:$H$3110,2,FALSE()),0) -> 0
A2969: Jefferson | B2969: Washington | C2969: =VLOOKUP(B2969,StateAbb!$A$3:$C$62,3,FALSE()) -> WA | D2969: Jefferson-Washington | E2969: =CONCATENATE(C2969,A2969) -> WAJefferson | F2969: 31 | G2969: 1 | H2969: =IFERROR(VLOOKUP(G2969,county_reeds_corrected0310!$G$1:$H$3110,2,FALSE()),0) -> 2
A2970: King | B2970: Washington | C2970: =VLOOKUP(B2970,StateAbb!$A$3:$C$62,3,FALSE()) -> WA | D2970: King-Washington | E2970: =CONCATENATE(C2970,A2970) -> WAKing | F2970: 33 | G2970: 3 | H2970: =IFERROR(VLOOKUP(G2970,county_reeds_corrected0310!$G$1:$H$3110,2,FALSE()),0) -> 1
A2971: Kitsap | B2971: Washington | C2971: =VLOOKUP(B2971,StateAbb!$A$3:$C$62,3,FALSE()) -> WA | D2971: Kitsap-Washington | E2971: =CONCATENATE(C2971,A2971) -> WAKitsap | F2971: 35 | G2971: 3 | H2971: =IFERROR(VLOOKUP(G2971,county_reeds_corrected0310!$G$1:$H$3110,2,FALSE()),0) -> 1
A2972: Kittitas | B2972: Washington | C2972: =VLOOKUP(B2972,StateAbb!$A$3:$C$62,3,FALSE()) -> WA | D2972: Kittitas-Washington | E2972: =CONCATENATE(C2972,A2972) -> WAKittitas | F2972: 37 | G2972: 4 | H2972: =IFERROR(VLOOKUP(G2972,county_reeds_corrected0310!$G$1:$H$3110,2,FALSE()),0) -> 1
A2973: Klickitat | B2973: Washington | C2973: =VLOOKUP(B2973,StateAbb!$A$3:$C$62,3,FALSE()) -> WA | D2973: Klickitat-Washington | E2973: =CONCATENATE(C2973,A2973) -> WAKlickitat | F2973: 39 | G2973: 5 | H2973: =IFERROR(VLOOKUP(G2973,county_reeds_corrected0310!$G$1:$H$3110,2,FALSE()),0) -> 2
A2974: Lewis | B2974: Washington | C2974: =VLOOKUP(B2974,StateAbb!$A$3:$C$62,3,FALSE()) -> WA | D2974: Lewis-Washington | E2974: =CONCATENATE(C2974,A2974) -> WALewis | F2974: 41 | G2974: 5 | H2974: =IFERROR(VLOOKUP(G2974,county_reeds_corrected0310!$G$1:$H$3110,2,FALSE()),0) -> 2
A2975: Lincoln | B2975: Washington | C2975: =VLOOKUP(B2975,StateAbb!$A$3:$C$62,3,FALSE()) -> WA | D2975: Lincoln-Washington | E2975: =CONCATENATE(C2975,A2975) -> WALincoln | F2975: 43 | G2975: 8 | H2975: =IFERROR(VLOOKUP(G2975,county_reeds_corrected0310!$G$1:$H$3110,2,FALSE()),0) -> 3
A2976: Mason | B2976: Washington | C2976: =VLOOKUP(B2976,StateAbb!$A$3:$C$62,3,FALSE()) -> WA | D2976: Mason-Washington | E2976: =CONCATENATE(C2976,A2976) -> WAMason | F2976: 45 | G2976: 1 | H2976: =IFERROR(VLOOKUP(G2976,county_reeds_corrected0310!$G$1:$H$3110,2,FALSE()),0) -> 2
A2977: Okanogan | B2977: Washington | C2977: =VLOOKUP(B2977,StateAbb!$A$3:$C$62,3,FALSE()) -> WA | D2977: Okanogan-Washington | E2977: =CONCATENATE(C2977,A2977) -> WAOkanogan | F2977: 47 | G2977: 6 | H2977: =IFERROR(VLOOKUP(G2977,county_reeds_corrected0310!$G$1:$H$3110,2,FALSE()),0) -> 3
A2978: Pacific | B2978: Washington | C2978: =VLOOKUP(B2978,StateAbb!$A$3:$C$62,3,FALSE()) -> WA | D2978: Pacific-Washington | E2978: =CONCATENATE(C2978,A2978) -> WAPacific | F2978: 49 | G2978: 1 | H2978: =IFERROR(VLOOKUP(G2978,county_reeds_corrected0310!$G$1:$H$3110,2,FALSE()),0) -> 2
A2979: Pend Oreille | B2979: Washington | C2979: =VLOOKUP(B2979,StateAbb!$A$3:$C$62,3,FALSE()) -> WA | D2979: Pend Oreille-Washington | E2979: =CONCATENATE(C2979,A2979) -> WAPend Oreille | F2979: 51 | G2979: 8 | H2979: =IFERROR(VLOOKUP(G2979,county_reeds_corrected0310!$G$1:$H$3110,2,FALSE()),0) -> 3
A2980: Pierce | B2980: Washington | C2980: =VLOOKUP(B2980,StateAbb!$A$3:$C$62,3,FALSE()) -> WA | D2980: Pierce-Washington | E2980: =CONCATENATE(C2980,A2980) -> WAPierce | F2980: 53 | G2980: 3 | H2980: =IFERROR(VLOOKUP(G2980,county_reeds_corrected0310!$G$1:$H$3110,2,FALSE()),0) -> 1
... A3142: Weston | B3142: Wyoming | C3142: =VLOOKUP(B3142,StateAbb!$A$3:$C$62,3,FALSE()) -> WY | D3142: Weston-Wyoming | E3142: =CONCATENATE(C3142,A3142) -> WYWeston | F3142: 45 | G3142: 73 | H3142: =IFERROR(VLOOKUP(G3142,county_reeds_corrected0310!$G$1:$H$3110,2,FALSE()),0) -> 23

Sheet StateAbb
A1: State | B1: Standard | C1: Postal | D1: Capital City
B2: Abbreviation | C2: Abbreviation
A3: Alabama | B3: Ala. | C3: AL | D3: Montgomery
A4: Alaska | B4: Alaska | C4: AK | D4: Juneau
A5: Arizona | B5: Ariz. | C5: AZ | D5: Phoenix
A6: Arkansas | B6: Ark. | C6: AR | D6: Little Rock
A7: California | B7: Calif. | C7: CA | D7: Sacramento
A8: Colorado | B8: Colo. | C8: CO | D8: Denver
A9: Connecticut | B9: Conn. | C9: CT | D9: Hartford
A10: Delaware | B10: Del. | C10: DE | D10: Dover
A11: Florida | B11: Fla. | C11: FL | D11: Tallahassee
A12: Georgia | B12: Ga. | C12: GA | D12: Atlanta
A13: Hawaii | B13: Hawaii | C13: HI | D13: Honolulu
A14: Idaho | B14: Idaho | C14: ID | D14: Boise
... A61: Virgin Islands | B61: V.I. | C61: VI | D61: Charlotte Amalie

Sheet Sheet1
A1: DOE/EIA ORIS plant or facility code | B1: Plant state abbreviation | D1: Plant name
A2: ORISPL | B2: PSTATABB | C2: COUNTY | D2: PNAME | E2: alternative-ID | F2: PCA | G2: ResourceRegion
A3: 57053 | B3: AK | C3: Wade Hampton | D3: Alakanuk | E3: AKWade Hampton | F3: 0 | G3: 0
A4: 57053 | B4: AK | C4: Wade Hampton | D4: Alakanuk | E4: AKWade Hampton | F4: 0 | G4: 0
A5: 57053 | B5: AK | C5: Wade Hampton | D5: Alakanuk | E5: AKWade Hampton | F5: 0 | G5: 0
A6: 75 | B6: AK | C6: Anchorage | D6: Anchorage 1 | E6: AKAnchorage | F6: 0 | G6: 0
A7: 75 | B7: AK | C7: Anchorage | D7: Anchorage 1 | E7: AKAnchorage | F7: 0 | G7: 0
A8: 75 | B8: AK | C8: Anchorage | D8: Anchorage 1 | E8: AKAnchorage | F8: 0 | G8: 0
A9: 75 | B9: AK | C9: Anchorage | D9: Anchorage 1 | E9: AKAnchorage | F9: 0 | G9: 0
A10: 75 | B10: AK | C10: Anchorage | D10: Anchorage 1 | E10: AKAnchorage | F10: 0 | G10: 0
A11: 75 | B11: AK | C11: Anchorage | D11: Anchorage 1 | E11: AKAnchorage | F11: 0 | G11: 0
A12: 7462 | B12: AK | C12: Juneau | D12: Angoon | E12: AKJuneau | F12: 0 | G12: 0
A13: 7462 | B13: AK | C13: Juneau | D13: Angoon | E13: AKJuneau | F13: 0 | G13: 0
A14: 7462 | B14: AK | C14: Juneau | D14: Angoon | E14: AKJuneau | F14: 0 | G14: 0
... A21: 7250 | B21: AK | C21: Juneau | D21: Auke Bay | E21: AKJuneau | F21: 0 | G21: 0
A22: 79 | B22: AK | C22: Fairbanks | D22: Aurora Energy LLC Chena | E22: AKFairbanks | F22: =#N/A -> #N/A | G22: =#N/A -> #N/A
A23: 79 | B23: AK | C23: Fairbanks | D23: Aurora Energy LLC Chena | E23: AKFairbanks | F23: =#N/A -> #N/A | G23: =#N/A -> #N/A
A24: 79 | B24: AK | C24: Fairbanks | D24: Aurora Energy LLC Chena | E24: AKFairbanks | F24: =#N/A -> #N/A | G24: =#N/A -> #N/A
A25: 79 | B25: AK | C25: Fairbanks | D25: Aurora Energy LLC Chena | E25: AKFairbanks | F25: =#N/A -> #N/A | G25: =#N/A -> #N/A
A26: 7173 | B26: AK | C26: North Slope | D26: Barrow | E26: AKNorth Slope | F26: 0 | G26: 0
A27: 7173 | B27: AK | C27: North Slope | D27: Barrow | E27: AKNorth Slope | F27: 0 | G27: 0
A28: 7173 | B28: AK | C28: North Slope | D28: Barrow | E28: AKNorth Slope | F28: 0 | G28: 0
A29: 7173 | B29: AK | C29: North Slope | D29: Barrow | E29: AKNorth Slope | F29: 0 | G29: 0
A30: 7173 | B30: AK | C30: North Slope | D30: Barrow | E30: AKNorth Slope | F30: 0 | G30: 0
A31: 7173 | B31: AK | C31: North Slope | D31: Barrow | E31: AKNorth Slope | F31: 0 | G31: 0
A32: 7173 | B32: AK | C32: North Slope | D32: Barrow | E32: AKNorth Slope | F32: 0 | G32: 0
A33: 6580 | B33: AK | C33: Ketchikan | D33: Beaver Falls | E33: AKKetchikan | F33: =#N/A -> #N/A | G33: =#N/A -> #N/A
A34: 6580 | B34: AK | C34: Ketchikan | D34: Beaver Falls | E34: AKKetchikan | F34: =#N/A -> #N/A | G34: =#N/A -> #N/A
A35: 6580 | B35: AK | C35: Ketchikan | D35: Beaver Falls | E35: AKKetchikan | F35: =#N/A -> #N/A | G35: =#N/A -> #N/A
A36: 96 | B36: AK | C36: Kenai Peninsula | D36: Beluga | E36: AKKenai Peninsula | F36: 0 | G36: 0
A37: 96 | B37: AK | C37: Kenai Peninsula | D37: Beluga | E37: AKKenai Peninsula | F37: 0 | G37: 0
A38: 96 | B38: AK | C38: Kenai Peninsula | D38: Beluga | E38: AKKenai Peninsula | F38: 0 | G38: 0
A39: 96 | B39: AK | C39: Kenai Peninsula | D39: Beluga | E39: AKKenai Peninsula | F39: 0 | G39: 0
A40: 96 | B40: AK | C40: Kenai Peninsula | D40: Beluga | E40: AKKenai Peninsula | F40: 0 | G40: 0
A41: 96 | B41: AK | C41: Kenai Peninsula | D41: Beluga | E41: AKKenai Peninsula | F41: 0 | G41: 0
A42: 96 | B42: AK | C42: Kenai Peninsula | D42: Beluga | E42: AKKenai Peninsula | F42: 0 | G42: 0
A43: 6292 | B43: AK | C43: Kenai Peninsula | D43: Bernice Lake | E43: AKKenai Peninsula | F43: 0 | G43: 0
A44: 6292 | B44: AK | C44: Kenai Peninsula | D44: Bernice Lake | E44: AKKenai Peninsula | F44: 0 | G44: 0
A45: 6292 | B45: AK | C45: Kenai Peninsula | D45: Bernice Lake | E45: AKKenai Peninsula | F45: 0 | G45: 0
A46: 6566 | B46: AK | C46: Bethel | D46: Bethel | E46: AKBethel | F46: 0 | G46: 0
A47: 6566 | B47: AK | C47: Bethel | D47: Bethel | E47: AKBethel | F47: 0 | G47: 0
... A51: 6566 | B51: AK | C51: Bethel | D51: Bethel | E51: AKBethel | F51: 0 | G51: 0
A52: 7752 | B52: AK | C52: Prince of Wales | D52: Black Bear Lake | E52: AKPrince of Wales | F52: =#N/A -> #N/A | G52: =#N/A -> #N/A
A53: 93 | B53: AK | C53: Sitka | D53: Blue Lake | E53: AKSitka | F53: 0 | G53: 0
A54: 93 | B54: AK | C54: Sitka | D54: Blue Lake | E54: AKSitka | F54: 0 | G54: 0
A55: 7367 | B55: AK | C55: Kenai Peninsula | D55: Bradley Lake | E55: AKKenai Peninsula | F55: 0 | G55: 0
A56: 7367 | B56: AK | C56: Kenai Peninsula | D56: Bradley Lake | E56: AKKenai Peninsula | F56: 0 | G56: 0
A57: 7112 | B57: AK | C57: Ketchikan | D57: Centennial | E57: AKKetchikan | F57: =#N/A -> #N/A | G57: =#N/A -> #N/A
A58: 7168 | B58: AK | C58: Ketchikan | D58: Chester Lake | E58: AKKetchikan | F58: =#N/A -> #N/A | G58: =#N/A -> #N/A
A59: 6311 | B59: AK | C59: Bethel | D59: Chevak | E59: AKBethel | F59: 0 | G59: 0
A60: 6311 | B60: AK | C60: Bethel | D60: Chevak | E60: AKBethel | F60: 0 | G60: 0
A61: 6311 | B61: AK | C61: Bethel | D61: Chevak | E61: AKBethel | F61: 0 | G61: 0
A62: 6291 | B62: AK | C62: Kenai Peninsula | D62: Cooper Lake | E62: AKKenai Peninsula | F62: 0 | G62: 0
A63: 6291 | B63: AK | C63: Kenai Peninsula | D63: Cooper Lake | E63: AKKenai Peninsula | F63: 0 | G63: 0
A64: 421 | B64: AK | C64: Prince of Wales | D64: Craig | E64: AKPrince of Wales | F64: =#N/A -> #N/A | G64: =#N/A -> #N/A
A65: 421 | B65: AK | C65: Prince of Wales | D65: Craig | E65: AKPrince of Wales | F65: =#N/A -> #N/A | G65: =#N/A -> #N/A
A66: 421 | B66: AK | C66: Prince of Wales | D66: Craig | E66: AKPrince of Wales | F66: =#N/A -> #N/A | G66: =#N/A -> #N/A
A67: 421 | B67: AK | C67: Prince of Wales | D67: Craig | E67: AKPrince of Wales | F67: =#N/A -> #N/A | G67: =#N/A -> #N/A
A68: 56325 | B68: AK | C68: Fairbanks | D68: Delta Power | E68: AKFairbanks | F68: =#N/A -> #N/A | G68: =#N/A -> #N/A
A69: 109 | B69: AK | C69: Dillingham | D69: Dillingham | E69: AKDillingham | F69: 0 | G69: 0
A70: 109 | B70: AK | C70: Dillingham | D70: Dillingham | E70: AKDillingham | F70: 0 | G70: 0
A71: 109 | B71: AK | C71: Dillingham | D71: Dillingham | E71: AKDillingham | F71: 0 | G71: 0
A72: 109 | B72: AK | C72: Dillingham | D72: Dillingham | E72: AKDillingham | F72: 0 | G72: 0
A73: 109 | B73: AK | C73: Dillingham | D73: Dillingham | E73: AKDillingham | F73: 0 | G73: 0
A74: 109 | B74: AK | C74: Dillingham | D74: Dillingham | E74: AKDillingham | F74: 0 | G74: 0
A75: 109 | B75: AK | C75: Dillingham | D75: Dillingham | E75: AKDillingham | F75: 0 | G75: 0
A76: 109 | B76: AK | C76: Dillingham | D76: Dillingham | E76: AKDillingham | F76: 0 | G76: 0
A77: 7502 | B77: AK | C77: Aleutians West | D77: Dutch Harbor | E77: AKAleutians West | F77: 0 | G77: 0
A78: 7502 | B78: AK | C78: Aleutians West | D78: Dutch Harbor | E78: AKAleutians West | F78: 0 | G78: 0
A79: 7502 | B79: AK | C79: Aleutians West | D79: Dutch Harbor | E79: AKAleutians West | F79: 0 | G79: 0
A80: 7502 | B80: AK | C80: Aleutians West | D80: Dutch Harbor | E80: AKAleutians West | F80: 0 | G80: 0
... A84: 7502 | B84: AK | C84: Aleutians West | D84: Dutch Harbor | E84: AKAleutians West | F84: 0 | G84: 0
A85: 50392 | B85: AK | C85: Fairbanks | D85: Eielson AFB Central Heat & Power Plant | E85: AKFairbanks | F85: =#N/A -> #N/A | G85: =#N/A -> #N/A
A86: 50392 | B86: AK | C86: Fairbanks | D86: Eielson AFB Central Heat & Power Plant | E86: AKFairbanks | F86: =#N/A -> #N/A | G86: =#N/A -> #N/A
A87: 50392 | B87: AK | C87: Fairbanks | D87: Eielson AFB Central Heat & Power Plant | E87: AKFairbanks | F87: =#N/A -> #N/A | G87: =#N/A -> #N/A
A88: 50392 | B88: AK | C88: Fairbanks | D88: Eielson AFB Central Heat & Power Plant | E88: AKFairbanks | F88: =#N/A -> #N/A | G88: =#N/A -> #N/A
A89: 50392 | B89: AK | C89: Fairbanks | D89: Eielson AFB Central Heat & Power Plant | E89: AKFairbanks | F89: =#N/A -> #N/A | G89: =#N/A -> #N/A
A90: 50392 | B90: AK | C90: Fairbanks | D90: Eielson AFB Central Heat & Power Plant | E90: AKFairbanks | F90: =#N/A -> #N/A | G90: =#N/A -> #N/A
A91: 50392 | B91: AK | C91: Fairbanks | D91: Eielson AFB Central Heat & Power Plant | E91: AKFairbanks | F91: =#N/A -> #N/A | G91: =#N/A -> #N/A
A92: 50392 | B92: AK | C92: Fairbanks | D92: Eielson AFB Central Heat & Power Plant | E92: AKFairbanks | F92: =#N/A -> #N/A | G92: =#N/A -> #N/A
A93: 50392 | B93: AK | C93: Fairbanks | D93: Eielson AFB Central Heat & Power Plant | E93: AKFairbanks | F93: =#N/A -> #N/A | G93: =#N/A -> #N/A
A94: 50392 | B94: AK | C94: Fairbanks | D94: Eielson AFB Central Heat & Power Plant | E94: AKFairbanks | F94: =#N/A -> #N/A | G94: =#N/A -> #N/A
A95: 77 | B95: AK | C95: Matanuska-Susitna | D95: Eklutna Hydro Project | E95: AKMatanuska-Susitna | F95: 0 | G95: 0
A96: 77 | B96: AK | C96: Matanuska-Susitna | D96: Eklutna Hydro Project | E96: AKMatanuska-Susitna | F96: 0 | G96: 0
A97: 57060 | B97: AK | C97: Nome | D97: Elim | E97: AKNome | F97: 0 | G97: 0
A98: 57060 | B98: AK | C98: Nome | D98: Elim | E98: AKNome | F98: 0 | G98: 0
A99: 57060 | B99: AK | C99: Nome | D99: Elim | E99: AKNome | F99: 0 | G99: 0
A100: 6314 | B100: AK | C100: Bethel | D100: Emmonak | E100: AKBethel | F100: 0 | G100: 0
A101: 6314 | B101: AK | C101: Bethel | D101: Emmonak | E101: AKBethel | F101: 0 | G101: 0
A102: 6314 | B102: AK | C102: Bethel | D102: Emmonak | E102: AKBethel | F102: 0 | G102: 0
A103: 6314 | B103: AK | C103: Bethel | D103: Emmonak | E103: AKBethel | F103: 0 | G103: 0
A104: 6286 | B104: AK | C104: Fairbanks | D104: Fairbanks | E104: AKFairbanks | F104: =#N/A -> #N/A | G104: =#N/A -> #N/A
A105: 6286 | B105: AK | C105: Fairbanks | D105: Fairbanks | E105: AKFairbanks | F105: =#N/A -> #N/A | G105: =#N/A -> #N/A
A106: 6286 | B106: AK | C106: Fairbanks | D106: Fairbanks | E106: AKFairbanks | F106: =#N/A -> #N/A | G106: =#N/A -> #N/A
A107: 6286 | B107: AK | C107: Fairbanks | D107: Fairbanks | E107: AKFairbanks | F107: =#N/A -> #N/A | G107: =#N/A -> #N/A
A108: 56146 | B108: AK | C108: Prince of Wales | D108: False Island | E108: AKPrince of Wales | F108: =#N/A -> #N/A | G108: =#N/A -> #N/A
A109: 54834 | B109: AK | C109: Southeast Fairbanks | D109: Fort Greely Power Plant | E109: AKSoutheast Fairbanks | F109: 0 | G109: 0
A110: 54834 | B110: AK | C110: Southeast Fairbanks | D110: Fort Greely Power Plant | E110: AKSoutheast Fairbanks | F110: 0 | G110: 0
A111: 54834 | B111: AK | C111: Southeast Fairbanks | D111: Fort Greely Power Plant | E111: AKSoutheast Fairbanks | F111: 0 | G111: 0
A112: 54834 | B112: AK | C112: Southeast Fairbanks | D112: Fort Greely Power Plant | E112: AKSoutheast Fairbanks | F112: 0 | G112: 0
...
